hitml/__init__.py
hitml/hitml.py
hitml-0.1.0.dev0.dist-info/LICENSE
hitml-0.1.0.dev0.dist-info/WHEEL
hitml-0.1.0.dev0.dist-info/METADATA
hitml-0.1.0.dev0.dist-info/RECORD
